gitbackup/git_backup.py
gitbackup/githandler.py
git_backup_tool-0.1.2.dist-info/entry_points.txt
git_backup_tool-0.1.2.dist-info/WHEEL
git_backup_tool-0.1.2.dist-info/METADATA
git_backup_tool-0.1.2.dist-info/RECORD
