Metadata-Version: 2.1
Name: git-backup-tool
Version: 0.1.2
Summary: Backup Github, Bitbucket or Gitlab repositories
License: MIT
Author: Alexander Hieser
Author-email: Alexander.Hieser@online.de
Requires-Python: >=3.10,<4.0
Classifier: License :: OSI Approved :: MIT License
Classifier: Programming Language :: Python :: 3
Classifier: Programming Language :: Python :: 3.10
Requires-Dist: argparse
Requires-Dist: gitpython
Requires-Dist: progress
Requires-Dist: pylint
Requires-Dist: requests
